justcatit/__init__.py
justcatit/cat.py
justcatit/bin/AWSSDK.Core.dll
justcatit/bin/AWSSDK.S3.dll
justcatit/bin/Apache.Arrow.dll
justcatit/bin/AppSoftware.LicenceEngine.Common.dll
justcatit/bin/AppSoftware.LicenceEngine.KeyVerification.dll
justcatit/bin/Autofac.dll
justcatit/bin/AutofacSerilogIntegration.dll
justcatit/bin/Azure.Core.dll
justcatit/bin/Azure.Identity.dll
justcatit/bin/Azure.Storage.Blobs.dll
justcatit/bin/Azure.Storage.Common.dll
justcatit/bin/BouncyCastle.Cryptography.dll
justcatit/bin/ClickHouse.Client.dll
justcatit/bin/DocumentFormat.OpenXml.Framework.dll
justcatit/bin/DocumentFormat.OpenXml.dll
justcatit/bin/DuckDB.NET.Bindings.dll
justcatit/bin/DuckDB.NET.Data.dll
justcatit/bin/EPPlus.dll
justcatit/bin/Google.Api.Gax.Rest.dll
justcatit/bin/Google.Api.Gax.dll
justcatit/bin/Google.Apis.Auth.dll
justcatit/bin/Google.Apis.Core.dll
justcatit/bin/Google.Apis.Storage.v1.dll
justcatit/bin/Google.Apis.dll
justcatit/bin/Google.Cloud.Storage.V1.dll
justcatit/bin/Humanizer.dll
justcatit/bin/JC.Cat.Core.DuckDbExcelLoader.dll
justcatit/bin/JC.Cat.Core.DuckDbExcelLoader.pdb
justcatit/bin/JC.Cat.Core.Utils.dll
justcatit/bin/JC.Cat.Core.Utils.pdb
justcatit/bin/JC.Cat.Core.deps.json
justcatit/bin/JC.Cat.Core.dll
justcatit/bin/JC.Cat.Core.pdb
justcatit/bin/Microsoft.AnalysisServices.AdomdClient.dll
justcatit/bin/Microsoft.AnalysisServices.Runtime.Core.dll
justcatit/bin/Microsoft.AnalysisServices.Runtime.Windows.dll
justcatit/bin/Microsoft.Bcl.AsyncInterfaces.dll
justcatit/bin/Microsoft.CSharp.dll
justcatit/bin/Microsoft.Data.SqlClient.SNI.dll
justcatit/bin/Microsoft.Data.SqlClient.dll
justcatit/bin/Microsoft.DiaSymReader.Native.amd64.dll
justcatit/bin/Microsoft.Extensions.Configuration.Abstractions.dll
justcatit/bin/Microsoft.Extensions.Configuration.Binder.dll
justcatit/bin/Microsoft.Extensions.Configuration.FileExtensions.dll
justcatit/bin/Microsoft.Extensions.Configuration.Json.dll
justcatit/bin/Microsoft.Extensions.Configuration.dll
justcatit-2.1.0.dist-info/METADATA
justcatit-2.1.0.dist-info/WHEEL
justcatit-2.1.0.dist-info/top_level.txt
justcatit-2.1.0.dist-info/RECORD
