Metadata-Version: 2.4
Name: justcatit
Version: 2.1.0
Summary: CAT is a very simple tool that helps you automate tests for your data.
Author: Data Tools s.r.o.
Project-URL: Homepage, https://justcat.it
Project-URL: Documentation, https://docs.justcat.it
Project-URL: License, https://docs.justcat.it/docs/license
Project-URL: Privacy, https://docs.justcat.it/docs/privacy-policy
Keywords: testing,data,quality,automation,ETL
Classifier: Programming Language :: Python :: 3
Classifier: Operating System :: OS Independent
Requires-Python: >=3.8
Requires-Dist: pythonnet
